savarin
