Metadata-Version: 2.1
Name: savarin
Version: 0.0.3
Summary: Permite consumir un API de DummyJson
Home-page: https://github.com/Stevensavarin/codigofacilito_package
Author: Steven Savarin
Author-email: sawarinsteven@gmail.com
License: MIT
Keywords: codigofacilito
Classifier: Development Status :: 3 - Alpha
Classifier: Intended Audience :: Developers
Classifier: Topic :: Software Development :: Build Tools
Classifier: License :: OSI Approved :: MIT License
Classifier: Programming Language :: Python :: 3
License-File: LICENSE.txt
Requires-Dist: requests
